ghgql/__init__.py
ghgql/ghgql.py
ghgql-1.0.6.dist-info/LICENSE
ghgql-1.0.6.dist-info/WHEEL
ghgql-1.0.6.dist-info/METADATA
ghgql-1.0.6.dist-info/RECORD
