Metadata-Version: 2.1
Name: ghgql
Version: 1.0.6
Summary: Thin wrapper for interacting with the Github GraphQL API
Home-page: https://pypi.org/project/ghgql/
License: MIT
Keywords: Python,Github,GraphQL,API,Wrapper
Author: Konrad Kleine
Maintainer: Konrad Kleine
Requires-Python: >=3.8,<4
Classifier: License :: OSI Approved :: MIT License
Classifier: Programming Language :: Python :: 3
Classifier: Programming Language :: Python :: 3.8
Classifier: Programming Language :: Python :: 3.9
Classifier: Programming Language :: Python :: 3.10
Classifier: Programming Language :: Python :: 3.11
Requires-Dist: fnc (>=0.5.3,<0.6.0)
Requires-Dist: requests (>=2.28.1)
Project-URL: Documentation, https://ghgql.readthedocs.io/en/latest/?badge=latest
Project-URL: Repository, https://github.com/kwk/ghgql/
